hypertrace/__init__.py
hypertrace/env_var_settings.py
hypertrace/version.py
hypertrace/agent/__init__.py
hypertrace/agent/constants.py
hypertrace/agent/custom_logger.py
hypertrace/agent/autoinstrumentation/__init__.py
hypertrace/agent/autoinstrumentation/hypertrace_instrument.py
hypertrace/agent/autoinstrumentation/sitecustomize.py
hypertrace/agent/config/__init__.py
hypertrace/agent/config/config_pb2.py
hypertrace/agent/config/default.py
hypertrace/agent/config/environment.py
hypertrace/agent/config/file.py
hypertrace/agent/filter/__init__.py
hypertrace/agent/filter/registry.py
hypertrace/agent/init/__init__.py
hypertrace/agent/instrumentation/__init__.py
hypertrace/agent/instrumentation/instrumentation_definitions.py
hypertrace/agent/instrumentation/aiohttp/__init__.py
hypertrace/agent/instrumentation/aws_lambda/__init__.py
hypertrace/agent/instrumentation/boto/__init__.py
hypertrace/agent/instrumentation/botocore/__init__.py
hypertrace/agent/instrumentation/django/__init__.py
hypertrace/agent/instrumentation/django/django_auto_instrumentation_compat.py
hypertrace/agent/instrumentation/fast_api/__init__.py
hypertrace/agent/instrumentation/fast_api/fast_api_auto_instrumentation_compat.py
hypertrace/agent/instrumentation/flask/__init__.py
hypertrace/agent/instrumentation/grpc/__init__.py
hypertrace/agent/instrumentation/mysql/__init__.py
hypertrace/agent/instrumentation/postgresql/__init__.py
hypertrace/agent/instrumentation/requests/__init__.py
hypertrace_agent-0.15.1.dist-info/LICENSE
hypertrace_agent-0.15.1.dist-info/METADATA
hypertrace_agent-0.15.1.dist-info/WHEEL
hypertrace_agent-0.15.1.dist-info/entry_points.txt
hypertrace_agent-0.15.1.dist-info/top_level.txt
hypertrace_agent-0.15.1.dist-info/RECORD
