Metadata-Version: 2.1
Name: hypertrace-agent
Version: 0.15.1
Summary: Hypertrace Python Agent
Home-page: https://github.com/hypertrace/pythonagent
Author: Hypertrace
Author-email: community@hypertrace.org
Project-URL: Bug Tracker, https://github.com/hypertrace/pythonagent/issues
Classifier: Programming Language :: Python :: 3
Classifier: License :: OSI Approved :: Apache Software License
Classifier: Operating System :: OS Independent
Requires-Python: >=3.6
License-File: LICENSE
Requires-Dist: opentelemetry-api ==1.20.0
Requires-Dist: opentelemetry-exporter-otlp ==1.20.0
Requires-Dist: opentelemetry-exporter-zipkin ==1.20.0
Requires-Dist: opentelemetry-instrumentation ==0.41b0
Requires-Dist: opentelemetry-instrumentation-aiohttp-client ==0.41b0
Requires-Dist: opentelemetry-instrumentation-boto ==0.41b0
Requires-Dist: opentelemetry-instrumentation-botocore ==0.41b0
Requires-Dist: opentelemetry-instrumentation-wsgi ==0.41b0
Requires-Dist: opentelemetry-instrumentation-fastapi ==0.41b0
Requires-Dist: opentelemetry-instrumentation-flask ==0.41b0
Requires-Dist: opentelemetry-instrumentation-mysql ==0.41b0
Requires-Dist: opentelemetry-instrumentation-psycopg2 ==0.41b0
Requires-Dist: opentelemetry-instrumentation-requests ==0.41b0
Requires-Dist: opentelemetry-instrumentation-grpc ==0.41b0
Requires-Dist: opentelemetry-instrumentation-django ==0.41b0
Requires-Dist: opentelemetry-instrumentation-aws-lambda ==0.41b0
Requires-Dist: opentelemetry-propagator-b3 ==1.20.0
Requires-Dist: opentelemetry-sdk ==1.20.0
Requires-Dist: opentelemetry-util-http ==0.41b0
Requires-Dist: deprecated ==1.2.12
Requires-Dist: google >=3.0.0
Requires-Dist: pyyaml
Requires-Dist: protobuf <=3.19.6
